ctm_ai/__init__.py
ctm_ai/chunks/__init__.py
ctm_ai/chunks/chunk.py
ctm_ai/chunks/chunk_manager.py
ctm_ai/configs/__init__.py
ctm_ai/configs/ctm_config_base.py
ctm_ai/ctms/__init__.py
ctm_ai/ctms/ctm.py
ctm_ai/executors/__init__.py
ctm_ai/executors/executor_audio.py
ctm_ai/executors/executor_base.py
ctm_ai/executors/executor_code.py
ctm_ai/executors/executor_language.py
ctm_ai/executors/executor_math.py
ctm_ai/executors/executor_search.py
ctm_ai/executors/executor_video.py
ctm_ai/executors/executor_vision.py
ctm_ai/fusers/__init__.py
ctm_ai/fusers/fuser_base.py
ctm_ai/fusers/fuser_language.py
ctm_ai/graphs/__init__.py
ctm_ai/graphs/processor_graph.py
ctm_ai/messengers/__init__.py
ctm_ai/messengers/message.py
ctm_ai/messengers/messenger_audio.py
ctm_ai/messengers/messenger_base.py
ctm_ai/messengers/messenger_code.py
ctm_ai/messengers/messenger_language.py
ctm_ai/messengers/messenger_math.py
ctm_ai/messengers/messenger_search.py
ctm_ai/messengers/messenger_video.py
ctm_ai/messengers/messenger_vision.py
ctm_ai/processors/__init__.py
ctm_ai/processors/processor_audio.py
ctm_ai/processors/processor_base.py
ctm_ai/processors/processor_code.py
ctm_ai/processors/processor_language.py
ctm_ai/processors/processor_math.py
ctm_ai/processors/processor_search.py
ctm_ai/processors/processor_video.py
ctm_ai/processors/processor_vision.py
ctm_ai/scorers/__init__.py
ctm_ai/scorers/scorer_base.py
ctm_ai/scorers/scorer_language.py
ctm_ai/supervisors/__init__.py
ctm_ai/supervisors/supervisor_base.py
ctm_ai/supervisors/supervisor_language.py
ctm_ai/utils/__init__.py
ctm_ai/utils/error_handler.py
ctm_ai/utils/loader.py
ctm_ai/utils/logger.py
ctm_ai/utils/tool.py
ctm_ai-0.0.1.dist-info/LICENSE
ctm_ai-0.0.1.dist-info/METADATA
ctm_ai-0.0.1.dist-info/WHEEL
ctm_ai-0.0.1.dist-info/RECORD
