Metadata-Version: 2.3
Name: ctm-ai
Version: 0.0.1
Summary: A cognitive architecture motivated by consciousness turing machine.
License: Apache 2.0 License
Author: Haofei Yu
Author-email: yuhaofei44@gmail.com
Requires-Python: >=3.9,<3.12
Classifier: License :: Other/Proprietary License
Classifier: Programming Language :: Python :: 3
Classifier: Programming Language :: Python :: 3.9
Classifier: Programming Language :: Python :: 3.10
Classifier: Programming Language :: Python :: 3.11
Requires-Dist: beartype
Requires-Dist: google-generativeai
Requires-Dist: huggingface_hub (==0.27.1)
Requires-Dist: moviepy
Requires-Dist: mypy (>=1.8.0,<2.0.0)
Requires-Dist: openai (>=1.59.7,<2.0.0)
Requires-Dist: opencv-python
Requires-Dist: pydantic (>=2.10.5,<3.0.0)
Requires-Dist: requests
Requires-Dist: scikit_learn (==1.6.1)
Requires-Dist: sockio
Requires-Dist: termcolor
Requires-Dist: types-requests
Requires-Dist: wordfreq
